{
  "navigation": [
    {
      "icon": "ri-dashboard-line",
      "route": "/",
      "label": "Dashboard"
    },
    {
      "icon": "ri-book-read-line",
      "route": "/study-material",
      "label": "Study Material"
    },
    {
      "icon": "ri-currency-line",
      "route": "/test-series",
      "label": "Test Series"
    },
    {
      "icon": "ri-line-chart-line",
      "route": "/analytics",
      "label": "Analytics"
    },
    {
      "icon": "ri-group-line",
      "route": "/profile",
      "label": "Profile"
    },
    {
      "icon": "ri-question-line",
      "route": "/help-support",
      "label": "Help & Support"
    },
    {
      "icon": "ri-save-line",
      "route": "/analytics-reports",
      "label": "Store"
    }
  ]
 
}
